logzilla/__init__.py
logzilla/logzilla.py
logzilla-0.1.0.dist-info/LICENSE
logzilla-0.1.0.dist-info/METADATA
logzilla-0.1.0.dist-info/WHEEL
logzilla-0.1.0.dist-info/RECORD
