Metadata-Version: 2.1
Name: logzilla
Version: 0.1.0
Summary: Python logger wrapper for logging to console and file
Home-page: https://github.com/tomoum/logzilla
License: MIT
Author: Muhab Tomoum
Author-email: muhabtomoum@gmail.com
Requires-Python: >=3.8.1,<4.0
Classifier: Development Status :: 3 - Alpha
Classifier: Intended Audience :: Developers
Classifier: License :: OSI Approved :: MIT License
Classifier: Programming Language :: Python :: 3
Classifier: Programming Language :: Python :: 3.9
Classifier: Programming Language :: Python :: 3.10
Classifier: Programming Language :: Python :: 3.11
Classifier: Programming Language :: Python :: 3 :: Only
Classifier: Programming Language :: Python :: 3.10
Classifier: Programming Language :: Python :: 3.8
Classifier: Programming Language :: Python :: 3.9
Project-URL: Documentation, https://github.com/tomoum/logzilla#readme
Project-URL: Repository, https://github.com/tomoum/logzilla
